dns_messages/__init__.py
dns_messages/dns_objects/__init__.py
dns_messages/dns_objects/dns_message.py
dns_messages/dns_objects/dns_message_parser.py
dns_messages/dns_objects/opcode.py
dns_messages/dns_objects/question.py
dns_messages/dns_objects/rocde.py
dns_messages/dns_objects/rr_data/A.py
dns_messages/dns_objects/rr_data/AAAA.py
dns_messages/dns_objects/rr_data/CNAME.py
dns_messages/dns_objects/rr_data/HINFO.py
dns_messages/dns_objects/rr_data/MX.py
dns_messages/dns_objects/rr_data/PTR.py
dns_messages/dns_objects/rr_data/SOA.py
dns_messages/dns_objects/rr_data/TXT.py
dns_messages/dns_objects/rr_data/__init__.py
dns_messages/dns_objects/rr_data/resource_record.py
dns_messages/dns_objects/rr_data/items/__init__.py
dns_messages/dns_objects/rr_data/items/rr_class.py
dns_messages/dns_objects/rr_data/items/rr_type.py
dns_messages/dns_server/__init__.py
dns_messages/dns_server/dns_demo_server.py
dns_messages/dns_server/dns_server.py
dns_messages/exceptions/__init__.py
dns_messages/exceptions/parser_exception.py
dns_messages/utilities/__init__.py
dns_messages/utilities/bit_and_byte_manipulators.py
dns_messages/utilities/character_string_encoder_and_decoder.py
dns_messages/utilities/name_encoder_and_decoder.py
dns_messages-1.0.1.dist-info/LICENSE
dns_messages-1.0.1.dist-info/METADATA
dns_messages-1.0.1.dist-info/WHEEL
dns_messages-1.0.1.dist-info/top_level.txt
dns_messages-1.0.1.dist-info/RECORD
