Metadata-Version: 2.1
Name: dns-messages
Version: 1.0.1
Summary: A Python3 library for parsing and generating DNS messages
Home-page: https://github.com/wahlflo/dns-messages
Author: Florian Wahl
Author-email: florian.wahl.developer@gmail.com
Classifier: Programming Language :: Python :: 3
Classifier: License :: OSI Approved :: MIT License
Classifier: Operating System :: OS Independent
License-File: LICENSE
